LICENSE
MANIFEST.in
README.rst
setup.py
blanc_django_admin_skin/__init__.py
blanc_django_admin_skin.egg-info/PKG-INFO
blanc_django_admin_skin.egg-info/SOURCES.txt
blanc_django_admin_skin.egg-info/dependency_links.txt
blanc_django_admin_skin.egg-info/top_level.txt
blanc_django_admin_skin/static/admin/Makefile
blanc_django_admin_skin/static/admin/css/assets.css
blanc_django_admin_skin/static/admin/css/assets.less
blanc_django_admin_skin/static/admin/css/blanc1.4.css
blanc_django_admin_skin/static/admin/css/blanc1.4.less
blanc_django_admin_skin/static/admin/css/blanc_toolkit.css
blanc_django_admin_skin/static/admin/css/blanc_toolkit.less
blanc_django_admin_skin/static/admin/img/assets.png
blanc_django_admin_skin/static/admin/img/assets/icon_arrow-bottom-OVER.png
blanc_django_admin_skin/static/admin/img/assets/icon_arrow-bottom.png
blanc_django_admin_skin/static/admin/img/assets/icon_arrow-down-OVER.png
blanc_django_admin_skin/static/admin/img/assets/icon_arrow-down.png
blanc_django_admin_skin/static/admin/img/assets/icon_arrow-end-OVER.png
blanc_django_admin_skin/static/admin/img/assets/icon_arrow-end.png
blanc_django_admin_skin/static/admin/img/assets/icon_arrow-left-OVER.png
blanc_django_admin_skin/static/admin/img/assets/icon_arrow-left.png
blanc_django_admin_skin/static/admin/img/assets/icon_arrow-right-OVER.png
blanc_django_admin_skin/static/admin/img/assets/icon_arrow-right.png
blanc_django_admin_skin/static/admin/img/assets/icon_arrow-start-OVER.png
blanc_django_admin_skin/static/admin/img/assets/icon_arrow-start.png
blanc_django_admin_skin/static/admin/img/assets/icon_arrow-top-OVER.png
blanc_django_admin_skin/static/admin/img/assets/icon_arrow-top.png
blanc_django_admin_skin/static/admin/img/assets/icon_arrow-up-OVER.png
blanc_django_admin_skin/static/admin/img/assets/icon_arrow-up.png
blanc_django_admin_skin/static/admin/img/assets/icon_close-OVER.png
blanc_django_admin_skin/static/admin/img/assets/icon_close-WHITE.png
blanc_django_admin_skin/static/admin/img/assets/icon_close.png
blanc_django_admin_skin/static/admin/img/assets/icon_cog-OVER.png
blanc_django_admin_skin/static/admin/img/assets/icon_cog.png
