Metadata-Version: 1.1
Name: blanc-django-admin-skin
Version: 0.1.4
Summary: Blanc Admin Skin for Django
Home-page: http://www.blanctools.com/
Author: Steve Hawkes
Author-email: steve@hawkz.com
License: BSD-2
Platform: any
Classifier: Environment :: Web Environment
Classifier: Framework :: Django
Classifier: License :: OSI Approved :: BSD License
Classifier: Operating System :: OS Independent
Classifier: Programming Language :: Python
